bayeslite/__init__.py
bayeslite/ast.py
bayeslite/bayesdb.py
bayeslite/bql.py
bayeslite/bqlfn.py
bayeslite/codebook.py
bayeslite/compiler.py
bayeslite/core.py
bayeslite/exception.py
bayeslite/geweke_testing.py
bayeslite/grammar.py
bayeslite/guess.py
bayeslite/legacy_models.py
bayeslite/loggers.py
bayeslite/math_util.py
bayeslite/metamodel.py
bayeslite/parse.py
bayeslite/read_csv.py
bayeslite/read_pandas.py
bayeslite/remote.py
bayeslite/scan.py
bayeslite/schema.py
bayeslite/sessions.py
bayeslite/sqlite3_util.py
bayeslite/stats.py
bayeslite/txn.py
bayeslite/util.py
bayeslite/version.py
bayeslite/metamodels/__init__.py
bayeslite/metamodels/crosscat.py
bayeslite/metamodels/crosscat_generator_schema.py
bayeslite/metamodels/crosscat_theta.schema.json
bayeslite/metamodels/crosscat_theta_validator.py
bayeslite/metamodels/iid_gaussian.py
bayeslite/metamodels/nig_normal.py
bayeslite/metamodels/troll_rng.py
bayeslite/plex/__init__.py
bayeslite/plex/Actions.py
bayeslite/plex/DFA.py
bayeslite/plex/Errors.py
bayeslite/plex/Lexicons.py
bayeslite/plex/Machines.py
bayeslite/plex/Regexps.py
bayeslite/plex/Scanners.py
bayeslite/plex/Timing.py
bayeslite/plex/Traditional.py
bayeslite/plex/Transitions.py
bayeslite/shell/__init__.py
bayeslite/shell/core.py
bayeslite/shell/hook.py
bayeslite/shell/main.py
bayeslite/shell/pretty.py
bayeslite/weakprng/__init__.py
bayeslite/weakprng/chacha.py
bayeslite/weakprng/weakprng.py
bayeslite-0.1.8.dist-info/DESCRIPTION.rst
bayeslite-0.1.8.dist-info/METADATA
bayeslite-0.1.8.dist-info/metadata.json
bayeslite-0.1.8.dist-info/RECORD
bayeslite-0.1.8.dist-info/top_level.txt
bayeslite-0.1.8.dist-info/WHEEL
