Metadata-Version: 2.0
Name: bayeslite
Version: 0.1.8
Summary: BQL database built on SQLite3
Home-page: http://probcomp.csail.mit.edu/bayesdb
Author: MIT Probabilistic Computing Project
Author-email: bayesdb@mit.edu
License: Apache License, Version 2.0
Platform: UNKNOWN
Requires-Dist: bayeslite-apsw (>=3.8.0)
Requires-Dist: crosscat (==0.1.55)
Requires-Dist: jsonschema
Requires-Dist: numpy
Requires-Dist: requests
Requires-Dist: setuptools
